Python/__init__.py
Python/prueba.py
Python/prueba10.py
Python/prueba11.py
Python/prueba12.py
Python/prueba13.py
Python/prueba14.py
Python/prueba2.py
Python/prueba3.py
Python/prueba4.py
Python/prueba5.py
Python/prueba6.py
Python/prueba7.py
Python/prueba8.py
Python/prueba9.py
Python/EjericiciosTema1/SumaFracciones.py
Python/EjericiciosTema1/__init__.py
Python/EjericiciosTema1/cuentaAtras10_0.py
Python/EjericiciosTema1/ecuacion_primer_grado.py
programacion-0.1.3.1.dist-info/METADATA
programacion-0.1.3.1.dist-info/WHEEL
programacion-0.1.3.1.dist-info/top_level.txt
programacion-0.1.3.1.dist-info/RECORD
